towerpy/__init__.py
towerpy/base.py
towerpy/towerpy_logosd.png
towerpy/attc/__init__.py
towerpy/attc/attc_zhzdr.py
towerpy/attc/lnxlibattenuationcorrection.so
towerpy/attc/r_att_refl.py
towerpy/attc/w64libattenuationcorrection.dll
towerpy/calib/__init__.py
towerpy/calib/calib_phidp.py
towerpy/calib/calib_zdr.py
towerpy/datavis/__init__.py
towerpy/datavis/rad_display.py
towerpy/datavis/rad_interactive.py
towerpy/datavis/tpy_cm.py
towerpy/datavis/tpy_colors.py
towerpy/eclass/__init__.py
towerpy/eclass/lnxlibclutterclassifier.so
towerpy/eclass/nme.py
towerpy/eclass/snr.py
towerpy/eclass/w64libclutterclassifier.dll
towerpy/eclass/mfs_cband/cal_mf_LDR_clutter.dat
towerpy/eclass/mfs_cband/cal_mf_LDR_precipi.dat
towerpy/eclass/mfs_cband/cal_mf_Rhv_clutter.dat
towerpy/eclass/mfs_cband/cal_mf_Rhv_precipi.dat
towerpy/eclass/mfs_cband/cal_mf_Vel_clutter.dat
towerpy/eclass/mfs_cband/cal_mf_Vel_precipi.dat
towerpy/eclass/mfs_cband/cal_mf_ZDR_clutter.dat
towerpy/eclass/mfs_cband/cal_mf_ZDR_precipi.dat
towerpy/eclass/mfs_cband/cal_mf_ZHH_clutter.dat
towerpy/eclass/mfs_cband/cal_mf_ZHH_precipi.dat
towerpy/eclass/mfs_cband/cal_mf_sPdp_clutter.dat
towerpy/eclass/mfs_cband/cal_mf_sPdp_precipi.dat
towerpy/eclass/mfs_cband/cal_mf_sRhv_clutter.dat
towerpy/eclass/mfs_cband/cal_mf_sRhv_precipi.dat
towerpy/eclass/mfs_cband/cal_mf_sZdr_clutter.dat
towerpy/eclass/mfs_cband/cal_mf_sZdr_precipi.dat
towerpy/eclass/mfs_cband/cal_mf_sZhh_clutter.dat
towerpy/eclass/mfs_cband/cal_mf_sZhh_precipi.dat
towerpy/eclass/mfs_xband/cal_mf_Rhv_clutter.dat
towerpy/eclass/mfs_xband/cal_mf_Rhv_precipi.dat
towerpy/eclass/mfs_xband/cal_mf_Vel_clutter.dat
towerpy/eclass/mfs_xband/cal_mf_Vel_precipi.dat
towerpy/eclass/mfs_xband/cal_mf_ZDR_clutter.dat
towerpy/eclass/mfs_xband/cal_mf_ZDR_precipi.dat
towerpy/eclass/mfs_xband/cal_mf_ZHH_clutter.dat
towerpy/eclass/mfs_xband/cal_mf_ZHH_precipi.dat
towerpy/eclass/mfs_xband/cal_mf_sPdp_clutter.dat
towerpy/eclass/mfs_xband/cal_mf_sPdp_precipi.dat
towerpy_rd-1.0.9.dist-info/LICENSE
towerpy_rd-1.0.9.dist-info/METADATA
towerpy_rd-1.0.9.dist-info/WHEEL
towerpy_rd-1.0.9.dist-info/top_level.txt
towerpy_rd-1.0.9.dist-info/RECORD
