Metadata-Version: 2.1
Name: towerpy-rd
Version: 1.0.9
Summary: Towerpy: an open-source toolbox for processing polarimetric radar data
Home-page: https://github.com/uobwatergroup/towerpy
Author: Daniel Sanchez-Rivas and Miguel A Rico-Ramirez
Author-email: Daniel Sanchez-Rivas <towerpy@icloud.com>, Miguel A Rico-Ramirez <M.A.Rico-Ramirez@bristol.ac.uk>
Project-URL: article, https://doi.org/10.1016/j.envsoft.2023.105746
Project-URL: documentation, https://towerpy.readthedocs.io/en/latest/
Project-URL: repository, https://github.com/uobwatergroup/towerpy
Classifier: Intended Audience :: Science/Research
Classifier: License :: OSI Approved :: GNU General Public License v3 (GPLv3)
Classifier: Operating System :: POSIX :: Linux
Classifier: Operating System :: Microsoft :: Windows
Classifier: Topic :: Scientific/Engineering
Classifier: Topic :: Scientific/Engineering :: Atmospheric Science
Requires-Python: >=3.9
License-File: LICENSE
Requires-Dist: numpy
Requires-Dist: matplotlib>=3.5.2
Requires-Dist: scipy
Requires-Dist: cartopy
Requires-Dist: netCDF4
